multiplier_halfadder/substractor.v
// File: FULL-ADDER using 
module substractor (
    input a,
    input b,
    output x, 
    output y,
    input borrow
);
    assign x =  (borrow & ~(a ^ b)) | ((~(a)) & b);
    assign y = a ^ ( b ^ borrow);
endmodule

Full substractor/time_subs.v
`timescale 1ns/1ps
module timing_subs;
  reg a, b, borrow;
  wire y, x;

  substractor uut (.a(a), .b(b), .y(y), .x(x), .borrow(borrow));

  initial begin
    $dumpfile("c");
    $dumpvars(0, timing_subs);

    a = 1; b = 1; borrow = 0;
    #5 a = 0; b = 1 ; borrow = x;
    #5 a = 1; b = 0;borrow = x;
    #5 a = 0; b = 1;borrow = x;
    #5 a = 1; b = 1;borrow = x;
    #5 a = 0; b = 0;borrow = x;
    #5 a = 1; b = 1;borrow = x;
    #5 a = 0; b = 1;borrow = x;
    #5 a = 0; b = 0;borrow = x;
    #5 $finish;
  end

  initial begin
    $monitor("time=%0t | a=%b b=%b y=%b x=%b z=%b", $time, a, b, y, x, borrow);
  end
endmodule

Full substractor/c.vcd
$date
	Mon Nov  3 15:41:46 2025
$end
$version
	Icarus Verilog
$end
$timescale
	1ps
$end
$scope module timing_subs $end
$var wire 1 ! y $end
$var wire 1 " x $end
$var reg 1 # a $end
$var reg 1 $ b $end
$var reg 1 % borrow $end
$scope module uut $end
$var wire 1 # a $end
$var wire 1 $ b $end
$var wire 1 % borrow $end
$var wire 1 " x $end
$var wire 1 ! y $end
$upscope $end
$upscope $end
$enddefinitions $end
$comment Show the parameter values. $end
$dumpall
$end
#0
$dumpvars
0%
1$
1#
0"
0!
$end
#5000
1"
1!
0#
#10000
0"
0!
1%
0$
1#
#15000
1"
1!
0%
1$
0#
#20000
1"
1!
1%
1#
#25000
1!
0$
0#
#30000
1!
1$
1#
#35000
0!
0#
#40000
1"
1!
0$
