and_gate.v
// File: FULL-ADDER using 
module and_gate (
    input a,
    input b,
    output x, 
    output y,
    input carry_in
);
    assign x =  (a & b) | (carry_in & (a ^ b)); //( ~(~(~((~(a & a) & ~(b & b))& ~(a & b))& carry_in) & ~(~(a & b) & ~(a & b)))
    assign y = (a ^ b) ^ carry_in;
endmodule

tb_and_gate.v
`timescale 1ns/1ps
module tb_and_gate;
  reg a, b, carry_in;
  wire y, x;

  and_gate uut (.a(a), .b(b), .y(y), .x(x), . carry_in(carry_in));

  initial begin
    $dumpfile("and_gate.vcd");
    $dumpvars(0, tb_and_gate);

    a = 1; b = 1; carry_in = 0;
    #5 a = 0; b = 1 ; carry_in = x;
    #5 a = 1; b = 0;carry_in = x;
    #5 a = 0; b = 1;carry_in = x;
    #5 a = 1; b = 1;carry_in = x;
    #5 a = 0; b = 0;carry_in = x;
    #5 a = 1; b = 1;carry_in = x;
    #5 a = 0; b = 1;carry_in = x;
    #5 a = 0; b = 0;carry_in = x;
    #5 $finish;
  end

  initial begin
    $monitor("time=%0t | a=%b b=%b y=%b x=%b z=%b", $time, a, b, y, x, carry_in);
  end
endmodule

Full Adder/and_gate.vcd
$date
	Mon Nov  3 11:36:02 2025
$end
$version
	Icarus Verilog
$end
$timescale
	1ps
$end
$scope module tb_and_gate $end
$var wire 1 ! y $end
$var wire 1 " x $end
$var reg 1 # a $end
$var reg 1 $ b $end
$var reg 1 % carry_in $end
$scope module uut $end
$var wire 1 # a $end
$var wire 1 $ b $end
$var wire 1 % carry_in $end
$var wire 1 " x $end
$var wire 1 ! y $end
$upscope $end
$upscope $end
$enddefinitions $end
$comment Show the parameter values. $end
$dumpall
$end
#0
$dumpvars
0%
1$
1#
1"
0!
$end
#5000
1%
0#
#10000
0$
1#
#15000
1$
0#
#20000
1!
1#
#25000
0"
0$
0#
#30000
1"
0!
0%
1$
1#
#35000
1%
0#
#40000
0"
1!
0$
